unipay-0.1.9.post1.dist-info/METADATA
unipay-0.1.9.post1.dist-info/WHEEL
unipay-0.1.9.post1.dist-info/entry_points.txt
unipay/__main__.py
unipay/api.py
unipay/assets/css/font-awesome@5.15.1-min.css
unipay/assets/css/style.css
unipay/assets/webfonts/fa-brands-400.woff2
unipay/db.py
unipay/front/package-lock.json
unipay/front/package.json
unipay/front/pnpm-lock.yaml
unipay/front/src/css/styles.css
unipay/front/tailwind.config.js
unipay/gen_qrcode.py
unipay/templates/index.html
unipay/templates/unipay.html
unipay/templates/wechatpay.html
unipay-0.1.9.post1.dist-info/RECORD
