Metadata-Version: 2.1
Name: unipay
Version: 0.1.9.post1
Author-Email: djkcyl <cyl@cyllive.cn>
License: MIT
Requires-Python: >=3.8
Requires-Dist: fastapi~=0.99.0
Requires-Dist: qrcode[pil]
Requires-Dist: peewee
Requires-Dist: uvicorn
Requires-Dist: jinja2
Requires-Dist: python-multipart>=0.0.6
Requires-Dist: click>=8.1.6
Requires-Dist: aiofiles>=23.2.1
Requires-Dist: skia-python>=87.5
Requires-Dist: pyzxing>=1.0.2
Requires-Dist: opencv-python>=4.8.0.76
